setup_selenium/__init__.py
setup_selenium/py.typed
setup_selenium/setup_selenium.py
setup_selenium_testing-1.0.5.dist-info/LICENSE
setup_selenium_testing-1.0.5.dist-info/METADATA
setup_selenium_testing-1.0.5.dist-info/WHEEL
setup_selenium_testing-1.0.5.dist-info/RECORD
