Metadata-Version: 2.3
Name: setup-selenium-testing
Version: 1.0.5
Summary: Setup Selenium for automation testing
License: MIT
Author: Marcel Wilson
Author-email: trenchrats+pypi@gmail.com
Requires-Python: >=3.9,<4.0
Classifier: Intended Audience :: Developers
Classifier: License :: OSI Approved :: MIT License
Classifier: Natural Language :: English
Classifier: Operating System :: OS Independent
Classifier: Programming Language :: Python :: 3
Classifier: Programming Language :: Python :: 3.9
Classifier: Programming Language :: Python :: 3.10
Classifier: Programming Language :: Python :: 3.11
Classifier: Programming Language :: Python :: 3.12
Classifier: Programming Language :: Python :: 3.13
Classifier: Programming Language :: Python :: 3 :: Only
Provides-Extra: dev
Provides-Extra: test
Requires-Dist: black ; extra == "dev"
Requires-Dist: mypy ; extra == "dev"
Requires-Dist: pytest ; extra == "dev" or extra == "test"
Requires-Dist: ruff (>=0.8.0) ; extra == "dev"
Requires-Dist: selenium (>=4.7.0)
Requires-Dist: semantic-version
Requires-Dist: tox ; extra == "dev" or extra == "test"
Requires-Dist: typing-extensions
Project-URL: Repository, https://github.com/bandophahita/setup_selenium
